[
  {
    "timestamp": "2026-04-17T16:29:53.750017",
    "changes": [
      "UPDATE episodes/ep-01.html (+9 shorts)",
      "UPDATE episodes/ep-02-28.html (+3 shorts)",
      "UPDATE index.html (shorts+episodes+JSON-LD)",
      "UPDATE sitemap.xml"
    ]
  },
  {
    "timestamp": "2026-04-21T15:48:15.696251",
    "changes": [
      "NEW episodes/ep-16.html",
      "UPDATE episodes/ep-01.html (+9 shorts)",
      "UPDATE episodes/ep-05-2026.html (+1 shorts)",
      "UPDATE episodes/ep-08-nhk.html (+1 shorts)",
      "UPDATE episodes/ep-13-ai.html (+1 shorts)",
      "UPDATE episodes/ep-12.html (+1 shorts)",
      "UPDATE episodes/ep-06-ez-do.html (+1 shorts)",
      "UPDATE episodes/ep-02-28.html (+4 shorts)",
      "UPDATE index.html (shorts+episodes+JSON-LD)",
      "UPDATE sitemap.xml"
    ]
  },
  {
    "timestamp": "2026-04-21T18:59:03.367727",
    "changes": [
      "UPDATE episodes/ep-05-2026.html (+1 shorts)",
      "UPDATE episodes/ep-08-nhk.html (+1 shorts)",
      "UPDATE episodes/ep-13-ai.html (+1 shorts)",
      "UPDATE episodes/ep-12.html (+1 shorts)",
      "UPDATE episodes/ep-06-ez-do.html (+1 shorts)",
      "UPDATE sitemap.xml"
    ]
  },
  {
    "timestamp": "2026-04-21T22:30:05.635830",
    "changes": [
      "UPDATE index.html (shorts+episodes+JSON-LD)",
      "UPDATE sitemap.xml"
    ]
  },
  {
    "timestamp": "2026-04-22T10:10:30.509230",
    "changes": [
      "NEW episodes/ep-16.html",
      "UPDATE episodes/ep-01.html (+9 shorts)",
      "UPDATE episodes/ep-05-2026.html (+1 shorts)",
      "UPDATE episodes/ep-08-nhk.html (+1 shorts)",
      "UPDATE episodes/ep-13-ai.html (+1 shorts)",
      "UPDATE episodes/ep-12.html (+1 shorts)",
      "UPDATE episodes/ep-06-ez-do.html (+1 shorts)",
      "UPDATE episodes/ep-02-28.html (+4 shorts)",
      "UPDATE index.html (shorts+episodes+JSON-LD)",
      "UPDATE sitemap.xml"
    ]
  },
  {
    "timestamp": "2026-04-22T22:34:27.083566",
    "changes": [
      "UPDATE episodes/ep-10.html (+1 shorts)",
      "UPDATE episodes/ep-09.html (+1 shorts)",
      "UPDATE index.html (shorts+episodes+JSON-LD)",
      "UPDATE sitemap.xml"
    ]
  },
  {
    "timestamp": "2026-04-23T22:30:05.565493",
    "changes": [
      "UPDATE episodes/ep-01.html (+9 shorts)",
      "UPDATE episodes/ep-05-2026.html (+1 shorts)",
      "UPDATE episodes/ep-10.html (+1 shorts)",
      "UPDATE episodes/ep-08-nhk.html (+1 shorts)",
      "UPDATE episodes/ep-13-ai.html (+1 shorts)",
      "UPDATE episodes/ep-12.html (+1 shorts)",
      "UPDATE episodes/ep-09.html (+1 shorts)",
      "UPDATE episodes/ep-15.html (+1 shorts)",
      "UPDATE episodes/ep-14-ai.html (+1 shorts)",
      "UPDATE episodes/ep-06-ez-do.html (+1 shorts)",
      "UPDATE episodes/ep-02-28.html (+4 shorts)",
      "UPDATE index.html (shorts+episodes+JSON-LD)",
      "UPDATE sitemap.xml"
    ]
  },
  {
    "timestamp": "2026-04-24T22:40:17.750058",
    "changes": [
      "UPDATE episodes/ep-01.html (+9 shorts)",
      "UPDATE episodes/ep-05-2026.html (+1 shorts)",
      "UPDATE episodes/ep-10.html (+1 shorts)",
      "UPDATE episodes/ep-11-100.html (+1 shorts)",
      "UPDATE episodes/ep-08-nhk.html (+1 shorts)",
      "UPDATE episodes/ep-13-ai.html (+1 shorts)",
      "UPDATE episodes/ep-12.html (+1 shorts)",
      "UPDATE episodes/ep-09.html (+1 shorts)",
      "UPDATE episodes/ep-15.html (+1 shorts)",
      "UPDATE episodes/ep-14-ai.html (+1 shorts)",
      "UPDATE episodes/ep-06-ez-do.html (+1 shorts)",
      "UPDATE episodes/ep-02-28.html (+4 shorts)",
      "UPDATE index.html (shorts+episodes+JSON-LD)",
      "UPDATE sitemap.xml"
    ]
  }
]